{"cameraMode":{"drawMode":2,"name":"Shaded Wireframe","section":"Shading Mode"},"sceneLighting":true,"audioPlay":false,"sceneViewState":{"showFog":true,"showMaterialUpdate":false,"showSkybox":true,"showFlares":true,"showImageEffects":true,"showParticleSystems":true,"showVisualEffectGraphs":true,"m_FxEnabled":false},"in2DMode":false,"pivot":{"x":-10.865864753723145,"y":3.6940126419067385,"z":28.639585494995118},"rotation":{"x":0.3959731459617615,"y":-0.12201964855194092,"z":0.053178153932094577,"w":0.9085693359375},"size":7.825652599334717,"orthographic":false}